Single_Cycle_Processor_pipline/rtl/alu.sv
import packages::*;
module alu (
    input logic [31:0]rs1,rs2,
    input logic [3:0] alu_op,
    output logic [31:0]result
);
    always_comb begin 
        case (alu_op)
            ADD:  result = rs1 + rs2;                             // Addition
            SUB:  result = rs1 - rs2;                             // Subtraction
            XOR:  result = rs1 ^ rs2;                             // XOR
            OR:   result = rs1 | rs2;                             // OR
            AND:  result = rs1 & rs2;                             // AND
            SLL:  result = rs1 << rs2[4:0];                       // Shift Left Logical
            SRL:  result = rs1 >> rs2[4:0];                       // Shift Right Logical
            SRA:  result = $signed(rs1) >>> rs2[4:0];             // Shift Right Arithmetic
            SLT:  result = ($signed(rs1) < $signed(rs2)) ? 1 : 0; // Set Less Than (signed)
            SLTU: result = (rs1 < rs2) ? 1 : 0;                   // Set Less Than Unsigned
            PASS: result = rs2;                                   // PASS through rs2
            default: result = 32'b0;                              // Default case
        endcase
    end
endmodule

Single_Cycle_Processor_pipline/rtl/mux2_1.sv
module mux2_1 (
    input logic [31:0]input0,input1,
    input logic sel,
    output logic [31:0]out
);
assign out = (sel) ? input1 : input0;
endmodule

Single_Cycle_Processor/rtl/decoder.sv
import packages::*;
module decoder (
    input logic [31:0]instruction,
    output logic reg_wr,sel_B,
    output logic [31:0]immediate,
    output logic [3:0]alu_op
);
logic [2:0]funct3;
logic [6:0]opcode;
always_comb begin 
opcode = instruction[6:0];
funct3=instruction[14:12];
    case (opcode)
        R_TYPE:begin
            alu_op={funct3,instruction[30]};
            reg_wr=1'b1;
            sel_B=1'b0;
        end 
        I_TYPE:begin
            alu_op=ADD;
            reg_wr=1'b1;
            immediate = { {12{instruction[31]}}, instruction[30:20] };
            sel_B=1'b1;
        end
        default:begin
            alu_op=4'b0;
            reg_wr=1'b0;
            immediate =32'b0;
            sel_B=1'b0;
            end 
    endcase
        
end 
endmodule

Single_Cycle_Processor/rtl/registerfile.sv
module registerfile (
    input logic [4:0]raddr1,raddr2,waddr,
    input logic [31:0]wdata,
    input logic reg_wr,clock,reset,
    output logic [31:0]rdata1,rdata2
);
    logic [31:0]register_file [31:0]='{default:0};
    always_ff @( negedge clock ) begin 
        if (reset)begin
          register_file <= '{default:0};  
        end
        else if(reg_wr && (waddr!=5'b0)) begin
            register_file[waddr]<=wdata;
        end
    end
    always_comb begin 
        rdata1=register_file[raddr1];
        rdata2=register_file[raddr2];
    end

endmodule

Single_Cycle_Processor/rtl/instruction_memory.sv
module instruction_memory (
    input logic [31:0]addr,
    output logic [31:0]inst
);
    logic [31:0]inst_memory [31:0]='{default:0};
    always_comb begin
        inst=inst_memory[addr>>2];
    end

    initial begin
        inst_memory[0]=32'b0;
        inst_memory[1]=32'h05400413;
        inst_memory[2]=32'h03c00493;
        inst_memory[3]=32'h00940c63;
        inst_memory[4]=32'h00944663;
        inst_memory[5]=32'h40940433;
        inst_memory[6]=32'hff5ff06f;
        inst_memory[7]=32'h408484b3;
        inst_memory[8]=32'hfedff06f;
        inst_memory[9]=32'h00802423;
        inst_memory[10]=32'h00802503;
        inst_memory[11]=32'h0000006f;
    end
endmodule

Single_Cycle_Processor/rtl/pc_add.sv
module pc_add (
    input logic [31:0]pc_next,
    output logic [31:0]pc
);
always_comb begin
    pc=pc_next+4;
end
    
endmodule

Single_Cycle_Processor/rtl/pc.sv
module pc (
    output logic [31:0]pc,
    input logic clock,reset,
    input logic [31:0]pc_next
);
    always_ff @( posedge clock ) begin 
        if (reset) begin
            pc<=32'b0;
        end
        else begin
            pc<=pc_next;
        end
        
    end
endmodule

Single_Cycle_Processor/rtl/single_cycle_processor.sv
module single_cycle_processor (
    input logic reset,clock
);
logic [31:0]inst,pc,pc_next,result,rdata1,rdata2,rs2,immediate;
logic [3:0]alu_op;
logic reg_wr,sel_B;
//pc
pc _pc(.clock,.reset,.pc_next,.pc);
pc_add pc_4_add(.pc,.pc_next);
//instruction memory
instruction_memory _instruction_memory(.addr(pc_next),.inst);
//registerfile
registerfile _registerfile(.raddr1(inst[19:15]),.raddr2(inst[24:20]),.waddr(inst[11:7]),.wdata(result),.reg_wr,.rdata1,.rdata2,.clock,.reset);
//decoder
decoder _decoder(.instruction(inst),.reg_wr,.alu_op,.immediate,.sel_B);
//sel_B
mux2_1 Sel_B(.input0(rdata2),.input1(immediate),.out(rs2),.sel(sel_B));
//Alu
alu _alu(.rs1(rdata1),.rs2,.result,.alu_op);
endmodule

Single_Cycle_Processor/rtl/single_cycle_tb.sv
module single_cycle_tb;

    // Signals
    logic clock;
    logic reset;

    // Instantiate the processor
    single_cycle_processor uut (
        .clock(clock),
        .reset(reset)
    );

    // Clock generation
    initial begin
        clock = 0;
        forever #5 clock = ~clock; // Toggle clock every 5ns
    end

    // Test stimulus
    initial begin
        reset = 1;
        #10 reset = 0;  // De-assert reset after 10ns

        #100;  // Run simulation for 100ns
        $finish; // End simulation
    end

    // Dump waveforms
    initial begin
        $dumpfile("waveform.vcd");
        $dumpvars(0, single_cycle_tb);
    end

endmodule

Single_Cycle_Processor/rtl/waveform.vcd
$date
	Mon Feb 17 19:32:08 2025
$end
$version
	ModelSim Version 2020.1
$end
$timescale
	1ps
$end

$scope module single_cycle_tb $end
$var reg 1 ! clock $end
$var reg 1 " reset $end

$scope module uut $end
$var wire 1 # reset $end
$var wire 1 $ clock $end
$var reg 32 % inst [31:0] $end
$var reg 32 & pc [31:0] $end
$var reg 32 ' pc_next [31:0] $end
$var reg 32 ( result [31:0] $end
$var reg 32 ) rdata1 [31:0] $end
$var reg 32 * rdata2 [31:0] $end
$var reg 32 + rs2 [31:0] $end
$var reg 32 , immediate [31:0] $end
$var reg 4 - alu_op [3:0] $end
$var reg 1 . reg_wr $end
$var reg 1 / sel_B $end

$scope module _pc $end
$var wire 1 0 pc [31] $end
$var wire 1 1 pc [30] $end
$var wire 1 2 pc [29] $end
$var wire 1 3 pc [28] $end
$var wire 1 4 pc [27] $end
$var wire 1 5 pc [26] $end
$var wire 1 6 pc [25] $end
$var wire 1 7 pc [24] $end
$var wire 1 8 pc [23] $end
$var wire 1 9 pc [22] $end
$var wire 1 : pc [21] $end
$var wire 1 ; pc [20] $end
$var wire 1 < pc [19] $end
$var wire 1 = pc [18] $end
$var wire 1 > pc [17] $end
$var wire 1 ? pc [16] $end
$var wire 1 @ pc [15] $end
$var wire 1 A pc [14] $end
$var wire 1 B pc [13] $end
$var wire 1 C pc [12] $end
$var wire 1 D pc [11] $end
$var wire 1 E pc [10] $end
$var wire 1 F pc [9] $end
$var wire 1 G pc [8] $end
$var wire 1 H pc [7] $end
$var wire 1 I pc [6] $end
$var wire 1 J pc [5] $end
$var wire 1 K pc [4] $end
$var wire 1 L pc [3] $end
$var wire 1 M pc [2] $end
$var wire 1 N pc [1] $end
$var wire 1 O pc [0] $end
$var wire 1 $ clock $end
$var wire 1 # reset $end
$var reg 32 P pc_next [31:0] $end
$upscope $end

$scope module pc_4_add $end
$var wire 1 Q pc_next [31] $end
$var wire 1 R pc_next [30] $end
$var wire 1 S pc_next [29] $end
$var wire 1 T pc_next [28] $end
$var wire 1 U pc_next [27] $end
$var wire 1 V pc_next [26] $end
$var wire 1 W pc_next [25] $end
$var wire 1 X pc_next [24] $end
$var wire 1 Y pc_next [23] $end
$var wire 1 Z pc_next [22] $end
$var wire 1 [ pc_next [21] $end
$var wire 1 \ pc_next [20] $end
$var wire 1 ] pc_next [19] $end
$var wire 1 ^ pc_next [18] $end
$var wire 1 _ pc_next [17] $end
$var wire 1 ` pc_next [16] $end
$var wire 1 a pc_next [15] $end
$var wire 1 b pc_next [14] $end
$var wire 1 c pc_next [13] $end
$var wire 1 d pc_next [12] $end
$var wire 1 e pc_next [11] $end
$var wire 1 f pc_next [10] $end
$var wire 1 g pc_next [9] $end
$var wire 1 h pc_next [8] $end
$var wire 1 i pc_next [7] $end
$var wire 1 j pc_next [6] $end
$var wire 1 k pc_next [5] $end
$var wire 1 l pc_next [4] $end
$var wire 1 m pc_next [3] $end
$var wire 1 n pc_next [2] $end
$var wire 1 o pc_next [1] $end
$var wire 1 p pc_next [0] $end
$var reg 32 q pc [31:0] $end
$upscope $end

$scope module _instruction_memory $end
$var wire 1 r addr [31] $end
$var wire 1 s addr [30] $end
$var wire 1 t addr [29] $end
$var wire 1 u addr [28] $end
$var wire 1 v addr [27] $end
$var wire 1 w addr [26] $end
$var wire 1 x addr [25] $end
$var wire 1 y addr [24] $end
$var wire 1 z addr [23] $end
$var wire 1 { addr [22] $end
$var wire 1 | addr [21] $end
$var wire 1 } addr [20] $end
$var wire 1 ~ addr [19] $end
$var wire 1 !! addr [18] $end
$var wire 1 "! addr [17] $end
$var wire 1 #! addr [16] $end
$var wire 1 $! addr [15] $end
$var wire 1 %! addr [14] $end
$var wire 1 &! addr [13] $end
$var wire 1 '! addr [12] $end
$var wire 1 (! addr [11] $end
$var wire 1 )! addr [10] $end
$var wire 1 *! addr [9] $end
$var wire 1 +! addr [8] $end
$var wire 1 ,! addr [7] $end
$var wire 1 -! addr [6] $end
$var wire 1 .! addr [5] $end
$var wire 1 /! addr [4] $end
$var wire 1 0! addr [3] $end
$var wire 1 1! addr [2] $end
$var wire 1 2! addr [1] $end
$var wire 1 3! addr [0] $end
$var reg 32 4! inst [31:0] $end
$upscope $end

$scope module _registerfile $end
$var wire 1 5! raddr1 [4] $end
$var wire 1 6! raddr1 [3] $end
$var wire 1 7! raddr1 [2] $end
$var wire 1 8! raddr1 [1] $end
$var wire 1 9! raddr1 [0] $end
$var wire 1 :! raddr2 [4] $end
$var wire 1 ;! raddr2 [3] $end
$var wire 1 <! raddr2 [2] $end
$var wire 1 =! raddr2 [1] $end
$var wire 1 >! raddr2 [0] $end
$var wire 1 ?! waddr [4] $end
$var wire 1 @! waddr [3] $end
$var wire 1 A! waddr [2] $end
$var wire 1 B! waddr [1] $end
$var wire 1 C! waddr [0] $end
$var wire 1 D! wdata [31] $end
$var wire 1 E! wdata [30] $end
$var wire 1 F! wdata [29] $end
$var wire 1 G! wdata [28] $end
$var wire 1 H! wdata [27] $end
$var wire 1 I! wdata [26] $end
$var wire 1 J! wdata [25] $end
$var wire 1 K! wdata [24] $end
$var wire 1 L! wdata [23] $end
$var wire 1 M! wdata [22] $end
$var wire 1 N! wdata [21] $end
$var wire 1 O! wdata [20] $end
$var wire 1 P! wdata [19] $end
$var wire 1 Q! wdata [18] $end
$var wire 1 R! wdata [17] $end
$var wire 1 S! wdata [16] $end
$var wire 1 T! wdata [15] $end
$var wire 1 U! wdata [14] $end
$var wire 1 V! wdata [13] $end
$var wire 1 W! wdata [12] $end
$var wire 1 X! wdata [11] $end
$var wire 1 Y! wdata [10] $end
$var wire 1 Z! wdata [9] $end
$var wire 1 [! wdata [8] $end
$var wire 1 \! wdata [7] $end
$var wire 1 ]! wdata [6] $end
$var wire 1 ^! wdata [5] $end
$var wire 1 _! wdata [4] $end
$var wire 1 `! wdata [3] $end
$var wire 1 a! wdata [2] $end
$var wire 1 b! wdata [1] $end
$var wire 1 c! wdata [0] $end
$var wire 1 d! reg_wr $end
$var wire 1 $ clock $end
$var wire 1 # reset $end
$var reg 32 e! rdata1 [31:0] $end
$var reg 32 f! rdata2 [31:0] $end
$upscope $end

$scope module _decoder $end
$var wire 1 g! instruction [31] $end
$var wire 1 h! instruction [30] $end
$var wire 1 i! instruction [29] $end
$var wire 1 j! instruction [28] $end
$var wire 1 k! instruction [27] $end
$var wire 1 l! instruction [26] $end
$var wire 1 m! instruction [25] $end
$var wire 1 n! instruction [24] $end
$var wire 1 o! instruction [23] $end
$var wire 1 p! instruction [22] $end
$var wire 1 q! instruction [21] $end
$var wire 1 r! instruction [20] $end
$var wire 1 s! instruction [19] $end
$var wire 1 t! instruction [18] $end
$var wire 1 u! instruction [17] $end
$var wire 1 v! instruction [16] $end
$var wire 1 w! instruction [15] $end
$var wire 1 x! instruction [14] $end
$var wire 1 y! instruction [13] $end
$var wire 1 z! instruction [12] $end
$var wire 1 {! instruction [11] $end
$var wire 1 |! instruction [10] $end
$var wire 1 }! instruction [9] $end
$var wire 1 ~! instruction [8] $end
$var wire 1 !" instruction [7] $end
$var wire 1 "" instruction [6] $end
$var wire 1 #" instruction [5] $end
$var wire 1 $" instruction [4] $end
$var wire 1 %" instruction [3] $end
$var wire 1 &" instruction [2] $end
$var wire 1 '" instruction [1] $end
$var wire 1 (" instruction [0] $end
$var reg 1 )" reg_wr $end
$var reg 1 *" sel_B $end
$var reg 32 +" immediate [31:0] $end
$var reg 4 ," alu_op [3:0] $end
$var reg 3 -" funct3 [2:0] $end
$var reg 7 ." opcode [6:0] $end
$upscope $end

$scope module Sel_B $end
$var wire 1 /" input0 [31] $end
$var wire 1 0" input0 [30] $end
$var wire 1 1" input0 [29] $end
$var wire 1 2" input0 [28] $end
$var wire 1 3" input0 [27] $end
$var wire 1 4" input0 [26] $end
$var wire 1 5" input0 [25] $end
$var wire 1 6" input0 [24] $end
$var wire 1 7" input0 [23] $end
$var wire 1 8" input0 [22] $end
$var wire 1 9" input0 [21] $end
$var wire 1 :" input0 [20] $end
$var wire 1 ;" input0 [19] $end
$var wire 1 <" input0 [18] $end
$var wire 1 =" input0 [17] $end
$var wire 1 >" input0 [16] $end
$var wire 1 ?" input0 [15] $end
$var wire 1 @" input0 [14] $end
$var wire 1 A" input0 [13] $end
$var wire 1 B" input0 [12] $end
$var wire 1 C" input0 [11] $end
$var wire 1 D" input0 [10] $end
$var wire 1 E" input0 [9] $end
$var wire 1 F" input0 [8] $end
$var wire 1 G" input0 [7] $end
$var wire 1 H" input0 [6] $end
$var wire 1 I" input0 [5] $end
$var wire 1 J" input0 [4] $end
$var wire 1 K" input0 [3] $end
$var wire 1 L" input0 [2] $end
$var wire 1 M" input0 [1] $end
$var wire 1 N" input0 [0] $end
$var wire 1 O" input1 [31] $end
$var wire 1 P" input1 [30] $end
$var wire 1 Q" input1 [29] $end
$var wire 1 R" input1 [28] $end
$var wire 1 S" input1 [27] $end
$var wire 1 T" input1 [26] $end
$var wire 1 U" input1 [25] $end
$var wire 1 V" input1 [24] $end
$var wire 1 W" input1 [23] $end
$var wire 1 X" input1 [22] $end
$var wire 1 Y" input1 [21] $end
$var wire 1 Z" input1 [20] $end
$var wire 1 [" input1 [19] $end
$var wire 1 \" input1 [18] $end
$var wire 1 ]" input1 [17] $end
$var wire 1 ^" input1 [16] $end
$var wire 1 _" input1 [15] $end
$var wire 1 `" input1 [14] $end
$var wire 1 a" input1 [13] $end
$var wire 1 b" input1 [12] $end
$var wire 1 c" input1 [11] $end
$var wire 1 d" input1 [10] $end
$var wire 1 e" input1 [9] $end
$var wire 1 f" input1 [8] $end
$var wire 1 g" input1 [7] $end
$var wire 1 h" input1 [6] $end
$var wire 1 i" input1 [5] $end
$var wire 1 j" input1 [4] $end
$var wire 1 k" input1 [3] $end
$var wire 1 l" input1 [2] $end
$var wire 1 m" input1 [1] $end
$var wire 1 n" input1 [0] $end
$var wire 1 o" sel $end
$var reg 32 p" out [31:0] $end
$upscope $end

$scope module _alu $end
$var wire 1 q" rs1 [31] $end
$var wire 1 r" rs1 [30] $end
$var wire 1 s" rs1 [29] $end
$var wire 1 t" rs1 [28] $end
$var wire 1 u" rs1 [27] $end
$var wire 1 v" rs1 [26] $end
$var wire 1 w" rs1 [25] $end
$var wire 1 x" rs1 [24] $end
$var wire 1 y" rs1 [23] $end
$var wire 1 z" rs1 [22] $end
$var wire 1 {" rs1 [21] $end
$var wire 1 |" rs1 [20] $end
$var wire 1 }" rs1 [19] $end
$var wire 1 ~" rs1 [18] $end
$var wire 1 !# rs1 [17] $end
$var wire 1 "# rs1 [16] $end
$var wire 1 ## rs1 [15] $end
$var wire 1 $# rs1 [14] $end
$var wire 1 %# rs1 [13] $end
$var wire 1 &# rs1 [12] $end
$var wire 1 '# rs1 [11] $end
$var wire 1 (# rs1 [10] $end
$var wire 1 )# rs1 [9] $end
$var wire 1 *# rs1 [8] $end
$var wire 1 +# rs1 [7] $end
$var wire 1 ,# rs1 [6] $end
$var wire 1 -# rs1 [5] $end
$var wire 1 .# rs1 [4] $end
$var wire 1 /# rs1 [3] $end
$var wire 1 0# rs1 [2] $end
$var wire 1 1# rs1 [1] $end
$var wire 1 2# rs1 [0] $end
$var wire 1 3# rs2 [31] $end
$var wire 1 4# rs2 [30] $end
$var wire 1 5# rs2 [29] $end
$var wire 1 6# rs2 [28] $end
$var wire 1 7# rs2 [27] $end
$var wire 1 8# rs2 [26] $end
$var wire 1 9# rs2 [25] $end
$var wire 1 :# rs2 [24] $end
$var wire 1 ;# rs2 [23] $end
$var wire 1 <# rs2 [22] $end
$var wire 1 =# rs2 [21] $end
$var wire 1 ># rs2 [20] $end
$var wire 1 ?# rs2 [19] $end
$var wire 1 @# rs2 [18] $end
$var wire 1 A# rs2 [17] $end
$var wire 1 B# rs2 [16] $end
$var wire 1 C# rs2 [15] $end
$var wire 1 D# rs2 [14] $end
$var wire 1 E# rs2 [13] $end
$var wire 1 F# rs2 [12] $end
$var wire 1 G# rs2 [11] $end
$var wire 1 H# rs2 [10] $end
$var wire 1 I# rs2 [9] $end
$var wire 1 J# rs2 [8] $end
$var wire 1 K# rs2 [7] $end
$var wire 1 L# rs2 [6] $end
$var wire 1 M# rs2 [5] $end
$var wire 1 N# rs2 [4] $end
$var wire 1 O# rs2 [3] $end
$var wire 1 P# rs2 [2] $end
$var wire 1 Q# rs2 [1] $end
$var wire 1 R# rs2 [0] $end
$var wire 1 S# alu_op [3] $end
$var wire 1 T# alu_op [2] $end
$var wire 1 U# alu_op [1] $end
$var wire 1 V# alu_op [0] $end
$var reg 32 W# result [31:0] $end
$upscope $end
$upscope $end
$upscope $end
$enddefinitions $end
#0
$dumpvars
0!
1"
bx %
bx &
bx '
bx (
bx )
bx *
bx +
b0 ,
b0 -
0.
0/
bx P
bx q
bx 4!
bx e!
bx f!
0)"
0*"
b0 +"
b0 ,"
bx -"
bx ."
bx p"
bx W#
0$
1#
xO
xN
xM
xL
xK
xJ
xI
xH
xG
xF
xE
xD
xC
xB
xA
x@
x?
x>
x=
x<
x;
x:
x9
x8
x7
x6
x5
x4
x3
x2
x1
x0
xp
xo
xn
xm
xl
xk
xj
xi
xh
xg
xf
xe
xd
xc
xb
xa
x`
x_
x^
x]
x\
x[
xZ
xY
xX
xW
xV
xU
xT
xS
xR
xQ
x3!
x2!
x1!
x0!
x/!
x.!
x-!
x,!
x+!
x*!
x)!
x(!
x'!
x&!
x%!
x$!
x#!
x"!
x!!
x~
x}
x|
x{
xz
xy
xx
xw
xv
xu
xt
xs
xr
x9!
x8!
x7!
x6!
x5!
x>!
x=!
x<!
x;!
x:!
xC!
xB!
xA!
x@!
x?!
xc!
xb!
xa!
x`!
x_!
x^!
x]!
x\!
x[!
xZ!
xY!
xX!
xW!
xV!
xU!
xT!
xS!
xR!
xQ!
xP!
xO!
xN!
xM!
xL!
xK!
xJ!
xI!
xH!
xG!
xF!
xE!
xD!
0d!
x("
x'"
x&"
x%"
x$"
x#"
x""
x!"
x~!
x}!
x|!
x{!
xz!
xy!
xx!
xw!
xv!
xu!
xt!
xs!
xr!
xq!
xp!
xo!
xn!
xm!
xl!
xk!
xj!
xi!
xh!
xg!
xN"
xM"
xL"
xK"
xJ"
xI"
xH"
xG"
xF"
xE"
xD"
xC"
xB"
xA"
x@"
x?"
x>"
x="
x<"
x;"
x:"
x9"
x8"
x7"
x6"
x5"
x4"
x3"
x2"
x1"
x0"
x/"
0n"
0m"
0l"
0k"
0j"
0i"
0h"
0g"
0f"
0e"
0d"
0c"
0b"
0a"
0`"
0_"
0^"
0]"
0\"
0["
0Z"
0Y"
0X"
0W"
0V"
0U"
0T"
0S"
0R"
0Q"
0P"
0O"
0o"
x2#
x1#
x0#
x/#
x.#
x-#
x,#
x+#
x*#
x)#
x(#
x'#
x&#
x%#
x$#
x##
x"#
x!#
x~"
x}"
x|"
x{"
xz"
xy"
xx"
xw"
xv"
xu"
xt"
xs"
xr"
xq"
xR#
xQ#
xP#
xO#
xN#
xM#
xL#
xK#
xJ#
xI#
xH#
xG#
xF#
xE#
xD#
xC#
xB#
xA#
x@#
x?#
x>#
x=#
x<#
x;#
x:#
x9#
x8#
x7#
x6#
x5#
x4#
x3#
0V#
0U#
0T#
0S#
$end
#5
1!
1$
b0 P
b0 '
0p
0o
0n
0m
0l
0k
0j
0i
0h
0g
0f
0e
0d
0c
0b
0a
0`
0_
0^
0]
0\
0[
0Z
0Y
0X
0W
0V
0U
0T
0S
0R
0Q
03!
02!
01!
00!
0/!
0.!
0-!
0,!
0+!
0*!
0)!
0(!
0'!
0&!
0%!
0$!
0#!
0"!
0!!
0~
0}
0|
0{
0z
0y
0x
0w
0v
0u
0t
0s
0r
b0 4!
b100 q
b100 &
b0 %
0O
0N
1M
0L
0K
0J
0I
0H
0G
0F
0E
0D
0C
0B
0A
0@
0?
0>
0=
0<
0;
0:
09
08
07
06
05
04
03
02
01
00
0C!
0B!
0A!
0@!
0?!
0>!
0=!
0<!
0;!
0:!
09!
08!
07!
06!
05!
0("
0'"
0&"
0%"
0$"
0#"
0""
0!"
0~!
0}!
0|!
0{!
0z!
0y!
0x!
0w!
0v!
0u!
0t!
0s!
0r!
0q!
0p!
0o!
0n!
0m!
0l!
0k!
0j!
0i!
0h!
0g!
b0 ."
b0 -"
b0 e!
b0 f!
b0 *
b0 )
0N"
0M"
0L"
0K"
0J"
0I"
0H"
0G"
0F"
0E"
0D"
0C"
0B"
0A"
0@"
0?"
0>"
0="
0<"
0;"
0:"
09"
08"
07"
06"
05"
04"
03"
02"
01"
00"
0/"
b0 p"
b0 +
0R#
0Q#
0P#
0O#
0N#
0M#
0L#
0K#
0J#
0I#
0H#
0G#
0F#
0E#
0D#
0C#
0B#
0A#
0@#
0?#
0>#
0=#
0<#
0;#
0:#
09#
08#
07#
06#
05#
04#
03#
02#
01#
00#
0/#
0.#
0-#
0,#
0+#
0*#
0)#
0(#
0'#
0&#
0%#
0$#
0##
0"#
0!#
0~"
0}"
0|"
0{"
0z"
0y"
0x"
0w"
0v"
0u"
0t"
0s"
0r"
0q"
b0 W#
b0 (
0c!
0b!
0a!
0`!
0_!
0^!
0]!
0\!
0[!
0Z!
0Y!
0X!
0W!
0V!
0U!
0T!
0S!
0R!
0Q!
0P!
0O!
0N!
0M!
0L!
0K!
0J!
0I!
0H!
0G!
0F!
0E!
0D!
#10
0"
0!
0#
0$
#15
1!
1$
b100 P
b100 '
1n
11!
b1000 q
b1000 &
0M
1L
#20
0!
0$
#25
1!
1$
b1000 P
b1000 '
0n
1m
01!
10!
b1100 q
b1100 &
1M
#30
0!
0$
#35
1!
1$
b1100 P
b1100 '
1n
11!
b10000 q
b10000 &
0M
0L
1K
#40
0!
0$
#45
1!
1$
b10000 P
b10000 '
0n
0m
1l
01!
00!
1/!
b10100 q
b10100 &
1M
#50
0!
0$
#55
1!
1$
b10100 P
b10100 '
1n
11!
b11000 q
b11000 &
0M
1L
#60
0!
0$
#65
1!
1$
b11000 P
b11000 '
0n
1m
01!
10!
b11100 q
b11100 &
1M
#70
0!
0$
#75
1!
1$
b11100 P
b11100 '
1n
11!
b100000 q
b100000 &
0M
0L
0K
1J
#80
0!
0$
#85
1!
1$
b100000 P
b100000 '
0n
0m
0l
1k
01!
00!
0/!
1.!
b100100 q
b100100 &
1M
#90
0!
0$
#95
1!
1$
b100100 P
b100100 '
1n
11!
b101000 q
b101000 &
0M
1L
#100
0!
0$
#105
1!
1$
b101000 P
b101000 '
0n
1m
01!
10!
b101100 q
b101100 &
1M
